{
    "org": "pdixit@ibm.com",
    "label": "text2speech",
    "description": "Speech to text service using offline Espeak Tool",
    "public": true,
    "documentation": "",
    "url": "pdixitdomain.com.text2speech",
    "version": "0.0.3",
    "arch": "arm",
    "sharable": "singleton",
    "requiredServices": [
        {
            "url": "pdixitdomain.com.mqtt_broker",
            "org": "pdixit@ibm.com",
            "version": "0.0.1",
            "arch": "arm"
        }
    ],
    "userInput": [],
    "deployment": {
        "services": {
            "text2speech": {
                "devices": [],
                "image": "pdixit26/arm_text2speech:0.0.3",
                "privileged": true
            }
        }
    }
}